cvo20251229/__init__.py
cvo20251229/cvo20251229.py
cvo20251229/py.typed
cvo20251229-0.1.0.dist-info/WHEEL
cvo20251229-0.1.0.dist-info/METADATA
cvo20251229-0.1.0.dist-info/RECORD
