Metadata-Version: 2.3
Name: cvo20251229
Version: 0.1.0
Summary: Development flow as Paleofuturistic Python
Author: Paleofuturistic Python
Author-email: Paleofuturistic Python <me@here.now>
Classifier: Programming Language :: Python :: 3.12
Requires-Python: >=3.12
